supabase_mcp/__init__.py
supabase_mcp/_version.py
supabase_mcp/exceptions.py
supabase_mcp/logger.py
supabase_mcp/main.py
supabase_mcp/queries.py
supabase_mcp/settings.py
supabase_mcp/validators.py
supabase_mcp/api_manager/__init__.py
supabase_mcp/api_manager/api_manager.py
supabase_mcp/api_manager/api_safety_config.py
supabase_mcp/api_manager/api_spec_manager.py
supabase_mcp/api_manager/specs/api_spec.json
supabase_mcp/db_client/__init__.py
supabase_mcp/db_client/db_client.py
supabase_mcp/db_client/db_safety_config.py
supabase_mcp/sdk_client/__init__.py
supabase_mcp/sdk_client/auth_admin_models.py
supabase_mcp/sdk_client/auth_admin_sdk_spec.py
supabase_mcp/sdk_client/python_client.py
iflow_mcp_deploya_labs_supabase_mcp_server-0.1.0.dist-info/METADATA
iflow_mcp_deploya_labs_supabase_mcp_server-0.1.0.dist-info/WHEEL
iflow_mcp_deploya_labs_supabase_mcp_server-0.1.0.dist-info/entry_points.txt
iflow_mcp_deploya_labs_supabase_mcp_server-0.1.0.dist-info/licenses/LICENSE
iflow_mcp_deploya_labs_supabase_mcp_server-0.1.0.dist-info/RECORD
