Metadata-Version: 2.4
Name: iflow-mcp_deploya-labs_supabase-mcp-server
Version: 0.1.0
Summary: Unofficial Supabase MCP server that enables Cursor and Windsurf to manage your database and execute SQL queries
Project-URL: Homepage, https://github.com/Nopsled/supabase-mcp-server
Project-URL: Repository, https://github.com/Nopsled/supabase-mcp-server.git
Project-URL: Changelog, https://github.com/Nopsled/supabase-mcp-server/blob/main/CHANGELOG.MD
Project-URL: Documentation, https://github.com/Nopsled/supabase-mcp-server#readme
Author-email: Alexander Zuev <azuev@outlook.com>
License-Expression: Apache-2.0
License-File: LICENSE
Keywords: cursor,mcp,supabase,windsurf
Classifier: Development Status :: 4 - Beta
Classifier: Intended Audience :: Developers
Classifier: License :: OSI Approved :: Apache Software License
Classifier: Programming Language :: Python :: 3.13
Classifier: Topic :: Database :: Database Engines/Servers
Classifier: Topic :: Software Development :: Libraries :: Python Modules
Requires-Python: >=3.11
Requires-Dist: mcp[cli]>=1.2.1
Requires-Dist: psycopg2-binary>=2.9.10
Requires-Dist: supabase>=2.13.0
Requires-Dist: tenacity>=9.0.0
